[
  {
    "id-date": "2023-03-22 11:35:56.605237",
    "heading": "Еще новая заметка",
    "text": "заметка одна",
    "change_last_date": "2023-07-22 16:22:41.145915"
  },
  {
    "id-date": "2023-07-21 11:35:56.605237",
    "heading": "еще",
    "text": "заметка одна",
    "change_last_date": "2023-07-22 16:22:47.572516"
  },
  {
    "id-date": "2023-05-21 11:35:56.605237",
    "heading": "снова заметка",
    "text": "заметка одна",
    "change_last_date": "2023-07-22 16:23:08.833894"
  },
  {
    "id-date": "2023-07-22 15:46:31.455558",
    "heading": "Новая заметка",
    "text": "заметочка",
    "change_last_date": "2023-07-22 15:55:35.455441"
  },
  {
    "id-date": "2023-07-22 16:16:41.443482",
    "heading": "Еще одна новая заметка",
    "text": "замечаем заметку",
    "change_last_date": "2023-07-22 16:23:34.943819"
  }
]